docxhtml_converter/__init__.py
docxhtml_converter/docxhtml.py
docxhtml_converter/htmldocx.py
docxhtml_converter-0.1.3.dist-info/LICENSE
docxhtml_converter-0.1.3.dist-info/METADATA
docxhtml_converter-0.1.3.dist-info/WHEEL
docxhtml_converter-0.1.3.dist-info/entry_points.txt
docxhtml_converter-0.1.3.dist-info/top_level.txt
docxhtml_converter-0.1.3.dist-info/RECORD
