Metadata-Version: 2.1
Name: docxhtml-converter
Version: 0.1.3
Summary: A package to convert DOCX to HTML and HTML to DOCX with formatting preservation.
Home-page: https://github.com/MarlNox/docxhtml-converter
Author: Marl Nox
Author-email: marlind.maksuti@gmail.com
Classifier: Programming Language :: Python :: 3
Classifier: License :: OSI Approved :: MIT License
Classifier: Operating System :: OS Independent
Requires-Python: >=3.6
License-File: LICENSE
Requires-Dist: python-docx
Requires-Dist: beautifulsoup4
